veccl/__init__.py
veccl/libnccl-net-soft-bonding.so
veccl/libnccl.so
veccl-0.0.4.dist-info/LICENSE
veccl-0.0.4.dist-info/METADATA
veccl-0.0.4.dist-info/THIRD_PARTY_NOTICE
veccl-0.0.4.dist-info/WHEEL
veccl-0.0.4.dist-info/top_level.txt
veccl-0.0.4.dist-info/RECORD
