Metadata-Version: 2.2
Name: veccl
Version: 0.0.4
Summary: A high-performance communication library for AI training and inference, designed as a drop-in replacement for NCCL.
Author: Beijing Volcano Engine Technology Ltd.
License: Copyright (C) Beijing Volcano Engine Technology Ltd.
License-File: THIRD_PARTY_NOTICE
License-File: LICENSE
Dynamic: author
Dynamic: description
Dynamic: description-content-type
Dynamic: license
Dynamic: summary
